dask_fly/__about__.py
dask_fly/__init__.py
dask_fly/client.py
dask_fly/cluster.py
dask_fly/scheduler.py
dask_fly/utils.py
dask_fly/worker.py
dask_fly-0.0.2.dist-info/METADATA
dask_fly-0.0.2.dist-info/WHEEL
dask_fly-0.0.2.dist-info/licenses/LICENSE.txt
dask_fly-0.0.2.dist-info/RECORD
